CTkManager/CTkManager.py
CTkManager/__init__.py
ctkmanager-1.0.1.dist-info/licenses/LICENSE
ctkmanager-1.0.1.dist-info/METADATA
ctkmanager-1.0.1.dist-info/WHEEL
ctkmanager-1.0.1.dist-info/top_level.txt
ctkmanager-1.0.1.dist-info/RECORD
