Metadata-Version: 2.4
Name: CTkManager
Version: 1.0.1
Summary: CTkManager is a helper library designed to streamline CustomTkinter GUI development. It integrates PIL for image support and uses Enum to keep configuration clean and easy.
Author: McDjXdLol
Author-email: mcdjxdlol@gmail.com
Classifier: Programming Language :: Python :: 3
Classifier: Operating System :: OS Independent
Requires-Python: >=3.7
License-File: LICENSE
Requires-Dist: customtkinter
Requires-Dist: Pillow
Dynamic: author
Dynamic: author-email
Dynamic: classifier
Dynamic: description
Dynamic: description-content-type
Dynamic: license-file
Dynamic: requires-dist
Dynamic: requires-python
Dynamic: summary
